timexseries_clustering/__init__.py
timexseries_clustering/data_ingestion.py
timexseries_clustering/timeseries_container.py
timexseries_clustering/data_clustering/__init__.py
timexseries_clustering/data_clustering/distance_metric.py
timexseries_clustering/data_clustering/pipeline.py
timexseries_clustering/data_clustering/transformation.py
timexseries_clustering/data_clustering/validation_performances.py
timexseries_clustering/data_clustering/xcorr.py
timexseries_clustering/data_clustering/models/__init__.py
timexseries_clustering/data_clustering/models/gmm_cluster.py
timexseries_clustering/data_clustering/models/kmeans_cluster.py
timexseries_clustering/data_clustering/models/predictor.py
timexseries_clustering/data_visualization/__init__.py
timexseries_clustering/data_visualization/functions.py
timexseries_clustering-1.0.17.dist-info/LICENSE
timexseries_clustering-1.0.17.dist-info/METADATA
timexseries_clustering-1.0.17.dist-info/WHEEL
timexseries_clustering-1.0.17.dist-info/top_level.txt
timexseries_clustering-1.0.17.dist-info/RECORD
