Metadata-Version: 2.1
Name: timexseries-clustering
Version: 1.0.17
Summary: TIMEX-CLUSTERING is a framework for time-series-clustering-as-a-service
Home-page: https://github.com/uGR17/TIMEX_CLUSTERING
Author: Uriel Guadarrama Ramirez
Author-email: u.guadarrama@hotmail.com
License: GNU General Public License v3 (GPLv3)
Platform: UNKNOWN
Classifier: Programming Language :: Python :: 3.7
Classifier: License :: OSI Approved :: GNU General Public License v3 (GPLv3)
Classifier: Topic :: Scientific/Engineering :: Mathematics
Classifier: Topic :: Scientific/Engineering :: Information Analysis
License-File: LICENSE
Requires-Dist: dateparser (<2.0.0,>=1.0.0)
Requires-Dist: torch (>=1.7.0)
Requires-Dist: tslearn (>=0.5.0)
Requires-Dist: matplotlib (>=2.0.0)
Requires-Dist: plotly (>=5.5.0)
Requires-Dist: wheel (>=0.33.0)
Requires-Dist: colorhash (<2.0.0,>=1.0.3)
Requires-Dist: networkx (>=2.5.0)
Requires-Dist: dash (<2.0.0,>=1.19.0)
Requires-Dist: dash-bootstrap-components (>=0.11.3)
Requires-Dist: jupyter-dash (>=0.4.0)
Requires-Dist: pmdarima (<2.0.0,>=1.8.2)
Requires-Dist: gunicorn (<21.0.0,>=20.0.4)
Requires-Dist: sklearn (<0.1,>=0.0)
Requires-Dist: scipy (<2.0.0,>=1.6.0)
Requires-Dist: statsmodels (<0.13.0,>=0.12.2)
Requires-Dist: PyWavelets (>=1.2.0)
Requires-Dist: pytest (>=4.3.0)
Requires-Dist: Flask (>=1.0.4)
